babs/__init__.py
babs/_version.py
babs/base.py
babs/bootstrap.py
babs/check_setup.py
babs/cli.py
babs/constants.py
babs/container.py
babs/dict_cluster_systems.yaml
babs/generate_bidsapp_runscript.py
babs/generate_submit_script.py
babs/input_dataset.py
babs/input_datasets.py
babs/interaction.py
babs/merge.py
babs/scheduler.py
babs/system.py
babs/template_test_job.py
babs/update.py
babs/utils.py
babs/bids_skeletons/multi_ses_qsiprep.yaml
babs/bids_skeletons/no_ses_qsiprep.yaml
babs/templates/babs_proj_config.yaml.jinja2
babs/templates/bidsapp_pipeline_run.sh.jinja2
babs/templates/bidsapp_run.sh.jinja2
babs/templates/determine_zipfilename.sh.jinja2
babs/templates/filter_file.sh.jinja2
babs/templates/job_status_report.jinja
babs/templates/job_submit.yaml.jinja2
babs/templates/participant_job.sh.jinja2
babs/templates/test_array_job.sh.jinja2
babs/templates/test_job.sh.jinja2
babs/templates/unzip_inputds.sh.jinja2
babs/templates/zipping.sh.jinja2
babs-0.5.4.dist-info/METADATA
babs-0.5.4.dist-info/WHEEL
babs-0.5.4.dist-info/entry_points.txt
babs-0.5.4.dist-info/licenses/LICENSE
babs-0.5.4.dist-info/RECORD
